<?xml version="1.0" encoding="UTF-8"?>
<page id="0084">
<map name="Map" id="Map">
<art type="icon">
<coords><![CDATA[544,619]]></coords>
<icon><![CDATA[writing_booster]]></icon>
<pFunction><![CDATA[generic_gotopage]]></pFunction>
<scale><![CDATA[80]]></scale>
<title><![CDATA[Go to Writing Booster]]></title>
<page><![CDATA[146]]></page>
</art>
<art type="icon">
<coords><![CDATA[54,78]]></coords>
<icon><![CDATA[audio_button]]></icon>
<pFunction><![CDATA[audio_icon]]></pFunction>
<scale><![CDATA[82]]></scale>
<href><![CDATA[Top Notch 3 MP3 files/Unit_07/4-17_A_Listening_compreh_p84.mp3]]></href>
<title><![CDATA[Play audio]]></title>
</art>
<art type="icon">
<coords><![CDATA[436,204]]></coords>
<icon><![CDATA[tn_music_icon_left]]></icon>
<pFunction><![CDATA[audio_icon]]></pFunction>
<scale><![CDATA[82]]></scale>
<href><![CDATA[Top Notch 3 MP3 files/Unit_07/4-18_Song_Endless_Holida_p84.mp3]]></href>
<title><![CDATA[Play Song]]></title>
</art>
<art type="icon">
<coords><![CDATA[478,203]]></coords>
<icon><![CDATA[tn_music_icon_right]]></icon>
<pFunction><![CDATA[audio_icon]]></pFunction>
<scale><![CDATA[82]]></scale>
<href><![CDATA[Top Notch 3 MP3 files/Unit_07/4-19_Karaoke_Endless_Hol_p84.mp3]]></href>
<title><![CDATA[Play Karaoke Version]]></title>
</art>
</map>
</page>
